[
  {
    "id": "pol-1",
    "title": "前海自贸区银行结汇便利化进一步扩大试点范围",
    "source": "国家金融监督管理总局",
    "date": "2026-04-10",
    "category": "跨境金融",
    "tags": [
      "前海",
      "结汇便利化",
      "自贸区",
      "跨境金融"
    ],
    "summary": "国家金融监督管理总局批复扩大前海自贸区银行结汇便利化试点，新增多家外资银行试点资格，进一步简化跨境贸易投资结算流程。",
    "aiSummary": "【AI摘要】该政策旨在通过扩大前海自贸区银行结汇便利化试点，提升跨境资金流动效率。涉及外资银行首次获得试点资格，表明监管层对金融开放的积极态度。预计将对深圳外资银行业务量产生正面影响。",
    "keywords": [
      "前海自贸区",
      "结汇便利化",
      "外资银行",
      "跨境贸易",
      "金融开放"
    ],
    "applicableInstitutions": [
      "外资银行",
      "中资银行跨境业务部",
      "贸易企业"
    ],
    "riskLevel": "low",
    "sourceUrl": "https://www.nfra.gov.cn",
    "pdfUrl": ""
  },
  {
    "id": "pol-2",
    "title": "深圳启动科薪通科技人才贷款试点",
    "source": "深圳金融局",
    "date": "2026-04-08",
    "category": "金融科技",
    "tags": [
      "科薪通",
      "科技金融",
      "人才贷款",
      "深圳"
    ],
    "summary": "深圳市地方金融监管局联合市人社局推出「科薪通」试点，为深圳高层次科技人才提供专项信用贷款，最高额度500万元。",
    "aiSummary": "【AI摘要】「科薪通」是深圳在科技金融领域的重要创新，将人才价值转化为融资信用。该产品为高层次科技人才提供无抵押信用贷款，预计将吸引更多科技人才落户深圳。",
    "keywords": [
      "科技金融",
      "人才贷款",
      "信用贷款",
      "深圳创新"
    ],
    "applicableInstitutions": [
      "商业银行",
      "科技支行",
      "深圳金融机构"
    ],
    "riskLevel": "low",
    "sourceUrl": "https://jr.sz.gov.cn",
    "pdfUrl": ""
  },
  {
    "id": "pol-3",
    "title": "央行发布2026年第10号公告：进一步推动本外币一体化资金池",
    "source": "中国人民银行",
    "date": "2026-04-05",
    "category": "跨境金融",
    "tags": [
      "本外币",
      "资金池",
      "跨境",
      "跨国公司"
    ],
    "summary": "中国人民银行发布2026年第10号公告，进一步扩大本外币一体化资金池试点，简化跨国公司跨境资金集中运营管理。",
    "aiSummary": "【AI摘要】该公告是本外币一体化改革的重要步骤，简化了跨国公司跨境资金池管理，降低了企业合规成本。对深圳跨国公司总部经济有积极推动作用。",
    "keywords": [
      "本外币一体化",
      "资金池",
      "跨国公司",
      "跨境资金"
    ],
    "applicableInstitutions": [
      "跨国公司",
      "商业银行",
      "跨境支付机构"
    ],
    "riskLevel": "low",
    "sourceUrl": "https://www.pbc.gov.cn",
    "pdfUrl": ""
  },
  {
    "id": "pol-4",
    "title": "跨境理财通2.0数据发布：深圳地区收付规模达585.2亿元",
    "source": "中国人民银行",
    "date": "2026-04-01",
    "category": "跨境金融",
    "tags": [
      "跨境理财通",
      "大湾区",
      "理财",
      "深圳"
    ],
    "summary": "中国人民银行发布跨境理财通最新数据，截至2026年3月，深圳地区跨境理财通累计收付规模达585.2亿元，同比大幅增长。",
    "aiSummary": "【AI摘要】跨境理财通2.0版本自上线以来，深圳地区业务量增长显著。585.2亿元的累计规模显示大湾区居民对跨境理财产品的强劲需求。南向通和北向通均实现双位数增长。",
    "keywords": [
      "跨境理财通",
      "大湾区",
      "585亿",
      "理财产品"
    ],
    "applicableInstitutions": [
      "银行理财子公司",
      "港资银行",
      "证券公司"
    ],
    "riskLevel": "low",
    "sourceUrl": "https://www.pbc.gov.cn",
    "pdfUrl": ""
  },
  {
    "id": "pol-5",
    "title": "外管局深圳分局推动外汇便利化改革新举措",
    "source": "国家金融监督管理总局",
    "date": "2026-04-03",
    "category": "跨境金融",
    "tags": [
      "外汇管理",
      "便利化",
      "深圳",
      "外管局"
    ],
    "summary": "外管局深圳分局发布多项外汇便利化措施，包括简化经常项目外汇收支审核、扩大资本项目收入支付便利化等。",
    "aiSummary": "【AI摘要】外管局深圳分局的外汇便利化措施对标国际先进水平，重点简化了经常项目外汇收支审核流程。这是落实国务院「放管服」改革要求的具体体现。",
    "keywords": [
      "外汇便利化",
      "经常项目",
      "资本项目",
      "放管服"
    ],
    "applicableInstitutions": [
      "外资企业",
      "进出口企业",
      "商业银行"
    ],
    "riskLevel": "low",
    "sourceUrl": "https://www.safe.gov.cn/shenzhen/",
    "pdfUrl": ""
  },
  {
    "id": "pol-6",
    "title": "国务院关于深圳建设中国特色社会主义先行示范区金融改革实施方案（十五五版）",
    "source": "国务院",
    "date": "2026-03-25",
    "category": "银行监管",
    "tags": [
      "先行示范区",
      "金融改革",
      "十五五",
      "深圳"
    ],
    "summary": "国务院印发深圳金融改革实施方案（十五五版），明确深圳在跨境金融、科技金融、绿色金融三大领域先行先试的具体路径。",
    "aiSummary": "【AI摘要】这是深圳金融改革顶层设计的重大更新。十五五版方案在原有示范区政策基础上，新增了科技金融和绿色金融两大支柱，为深圳金融机构提供了清晰的政策方向。",
    "keywords": [
      "示范区",
      "金融改革",
      "十五五",
      "先行先试"
    ],
    "applicableInstitutions": [
      "深圳所有金融机构",
      "政府相关部门"
    ],
    "riskLevel": "low",
    "sourceUrl": "https://www.gov.cn",
    "pdfUrl": ""
  },
  {
    "id": "pol-7",
    "title": "深圳市十五五规划：GDP目标突破5万亿，研发投入强度超7%",
    "source": "十五五规划",
    "date": "2026-03-20",
    "category": "货币政策",
    "tags": [
      "十五五",
      "深圳",
      "GDP",
      "5万亿",
      "研发投入"
    ],
    "summary": "深圳市十五五规划正式发布，提出到2030年GDP突破5万亿元、研发投入强度超7%、新质生产力占GDP比重超40%等核心目标。",
    "aiSummary": "【AI摘要】深圳十五五规划的核心目标——GDP突破5万亿，意味着深圳经济体量将比肩中等发达国家水平。研发强度7%的指标已超过多数发达国家，体现深圳以创新驱动发展的决心。",
    "keywords": [
      "十五五",
      "5万亿GDP",
      "研发7%",
      "新质生产力"
    ],
    "applicableInstitutions": [
      "所有机构",
      "政府",
      "企业"
    ],
    "riskLevel": "low",
    "sourceUrl": "https://www.sz.gov.cn",
    "pdfUrl": ""
  },
  {
    "id": "pol-8",
    "title": "证监会发布科技企业上市「绿色通道」新规",
    "source": "证监会",
    "date": "2026-03-28",
    "category": "证券监管",
    "tags": [
      "证监会",
      "科技企业",
      "上市",
      "绿色通道"
    ],
    "summary": "证监会发布科技企业上市「绿色通道」实施细则，深圳前海、北京中关村等地科技企业可享受优先审核、简化流程等便利。",
    "aiSummary": "【AI摘要】证监会为科技企业开设上市「绿色通道」，这是资本市场支持科技创新的重大利好。深圳前海被纳入首批试点区域，预计将加速深圳科技企业上市进程。",
    "keywords": [
      "科技企业",
      "上市",
      "绿色通道",
      "前海"
    ],
    "applicableInstitutions": [
      "科技企业",
      "证券公司",
      "投行"
    ],
    "riskLevel": "medium",
    "sourceUrl": "https://www.csrc.gov.cn",
    "pdfUrl": ""
  },
  {
    "id": "pol-9",
    "title": "深圳金融机构绿色信贷余额突破8000亿",
    "source": "深圳金融局",
    "date": "2026-04-12",
    "category": "绿色金融",
    "tags": [
      "绿色金融",
      "信贷",
      "碳达峰",
      "深圳"
    ],
    "summary": "深圳金融局发布数据，截至2026年一季度末，深圳金融机构绿色信贷余额突破8000亿元，同比增长35%。",
    "aiSummary": "【AI摘要】深圳绿色信贷余额突破8000亿，显示深圳金融机构在绿色金融领域的积极作为。35%的同比增速远超传统信贷增速，绿色金融正成为银行新的增长极。",
    "keywords": [
      "绿色信贷",
      "8000亿",
      "碳达峰",
      "碳中和"
    ],
    "applicableInstitutions": [
      "商业银行",
      "绿色企业",
      "ESG基金"
    ],
    "riskLevel": "low",
    "sourceUrl": "https://jr.sz.gov.cn",
    "pdfUrl": ""
  },
  {
    "id": "pol-10",
    "title": "央行深圳分行发布数字人民币跨境支付新方案",
    "source": "中国人民银行",
    "date": "2026-03-15",
    "category": "金融科技",
    "tags": [
      "数字人民币",
      "跨境支付",
      "深圳",
      "大湾区"
    ],
    "summary": "央行深圳分行推出数字人民币跨境支付解决方案，率先在大湾区实现数字人民币与港币的实时兑换和跨境结算。",
    "aiSummary": "【AI摘要】数字人民币跨境支付是深圳金融创新的标志性成果。大湾区率先实现数字人民币与港币实时兑换，为人民币国际化提供了新的技术路径。",
    "keywords": [
      "数字人民币",
      "跨境支付",
      "大湾区",
      "实时兑换"
    ],
    "applicableInstitutions": [
      "商业银行",
      "支付机构",
      "跨境贸易企业"
    ],
    "riskLevel": "medium",
    "sourceUrl": "https://www.pbc.gov.cn",
    "pdfUrl": ""
  }
]